vanguardpkg/__init__.py
vanguardpkg/vanguard_commons.py
vg_commons_pkg-2.0.3.dist-info/METADATA
vg_commons_pkg-2.0.3.dist-info/WHEEL
vg_commons_pkg-2.0.3.dist-info/top_level.txt
vg_commons_pkg-2.0.3.dist-info/RECORD
